TaskBank/ImgAug.py
TaskBank/SciKit.py
TaskBank/TaskBank.py
TaskBank/__init__.py
TaskBank-0.1.12.dist-info/LICENCE
TaskBank-0.1.12.dist-info/METADATA
TaskBank-0.1.12.dist-info/WHEEL
TaskBank-0.1.12.dist-info/top_level.txt
TaskBank-0.1.12.dist-info/RECORD
