Metadata-Version: 2.1
Name: TaskBank
Version: 0.1.12
Summary: A library of machine learning tasks for HackDuck
Home-page: https://github.com/AlexandreKempf/TaskBank
Author: Alexandre Kempf
Author-email: alexanre.kempf@cri-paris.org
License: UNKNOWN
Platform: UNKNOWN
Classifier: Programming Language :: Python :: 3
Classifier: License :: OSI Approved :: MIT License
Classifier: Operating System :: OS Independent
Requires-Python: >=3.6
